MANIFEST.in
README.rst
doctools.py
setup.py
doctools.egg-info/PKG-INFO
doctools.egg-info/SOURCES.txt
doctools.egg-info/dependency_links.txt
doctools.egg-info/requires.txt
doctools.egg-info/top_level.txt