Metadata-Version: 1.0
Name: doctools
Version: 0.2.1
Summary: docblock manipulation utilities
Home-page: https://github.com/awagner83/doctools
Author: Adam Wagner
Author-email: awagner83@gmail.com
License: BSD3
Platform: UNKNOWN
Classifier: Development Status :: 4 - Beta
Classifier: Topic :: Software Development
Classifier: Intended Audience :: Developers
Classifier: Programming Language :: Python
